[{"danceability": 0.525, "energy": 0.819, "key": 0, "loudness": -7.017, "mode": 1, "speechiness": 0.067, "acousticness": 0.398, "instrumentalness": 0, "liveness": 0.98, "valence": 0.698, "tempo": 155.823, "type": "audio_features", "id": "5JTL91USvogeqs9huIpXk8", "uri": "spotify:track:5JTL91USvogeqs9huIpXk8", "track_href": "https://api.spotify.com/v1/tracks/5JTL91USvogeqs9huIpXk8", "analysis_url": "https://api.spotify.com/v1/audio-analysis/5JTL91USvogeqs9huIpXk8", "duration_ms": 205335, "time_signature": 4}, {"danceability": 0.563, "energy": 0.839, "key": 7, "loudness": -6.596, "mode": 0, "speechiness": 0.0488, "acousticness": 0.766, "instrumentalness": 0, "liveness": 0.873, "valence": 0.651, "tempo": 160.029, "type": "audio_features", "id": "2iH7RnVhofwr9NhaQ6r44K", "uri": "spotify:track:2iH7RnVhofwr9NhaQ6r44K", "track_href": "https://api.spotify.com/v1/tracks/2iH7RnVhofwr9NhaQ6r44K", "analysis_url": "https://api.spotify.com/v1/audio-analysis/2iH7RnVhofwr9NhaQ6r44K", "duration_ms": 227413, "time_signature": 4}, {"danceability": 0.442, "energy": 0.806, "key": 10, "loudness": -5.79, "mode": 1, "speechiness": 0.125, "acousticness": 0.58, "instrumentalness": 0, "liveness": 0.78, "valence": 0.591, "tempo": 149.427, "type": "audio_features", "id": "6LQQGxRzNLsWQtwgLe5fAm", "uri": "spotify:track:6LQQGxRzNLsWQtwgLe5fAm", "track_href": "https://api.spotify.com/v1/tracks/6LQQGxRzNLsWQtwgLe5fAm", "analysis_url": "https://api.spotify.com/v1/audio-analysis/6LQQGxRzNLsWQtwgLe5fAm", "duration_ms": 180853, "time_signature": 4}, {"danceability": 0.57, "energy": 0.888, "key": 7, "loudness": -9.044, "mode": 1, "speechiness": 0.05, "acousticness": 0.561, "instrumentalness": 0, "liveness": 0.93, "valence": 0.645, "tempo": 163.966, "type": "audio_features", "id": "6DjKWVAqXUvMaAzO4U4CIo", "uri": "spotify:track:6DjKWVAqXUvMaAzO4U4CIo", "track_href": "https://api.spotify.com/v1/tracks/6DjKWVAqXUvMaAzO4U4CIo", "analysis_url": "https://api.spotify.com/v1/audio-analysis/6DjKWVAqXUvMaAzO4U4CIo", "duration_ms": 196307, "time_signature": 4}, {"danceability": 0.624, "energy": 0.734, "key": 4, "loudness": -6.498, "mode": 0, "speechiness": 0.0475, "acousticness": 0.516, "instrumentalness": 0, "liveness": 0.828, "valence": 0.499, "tempo": 139.905, "type": "audio_features", "id": "65vJAh07BdwurqR9SRa6f8", "uri": "spotify:track:65vJAh07BdwurqR9SRa6f8", "track_href": "https://api.spotify.com/v1/tracks/65vJAh07BdwurqR9SRa6f8", "analysis_url": "https://api.spotify.com/v1/audio-analysis/65vJAh07BdwurqR9SRa6f8", "duration_ms": 198678, "time_signature": 4}, {"danceability": 0.483, "energy": 0.912, "key": 7, "loudness": -7.164, "mode": 0, "speechiness": 0.0968, "acousticness": 0.474, "instrumentalness": 0, "liveness": 0.823, "valence": 0.526, "tempo": 106.286, "type": "audio_features", "id": "109AZuGAl3xtTgxwbonnEb", "uri": "spotify:track:109AZuGAl3xtTgxwbonnEb", "track_href": "https://api.spotify.com/v1/tracks/109AZuGAl3xtTgxwbonnEb", "analysis_url": "https://api.spotify.com/v1/audio-analysis/109AZuGAl3xtTgxwbonnEb", "duration_ms": 195693, "time_signature": 4}, {"danceability": 0.503, "energy": 0.755, "key": 8, "loudness": -6.21, "mode": 1, "speechiness": 0.064, "acousticness": 0.461, "instrumentalness": 0, "liveness": 0.912, "valence": 0.627, "tempo": 166.644, "type": "audio_features", "id": "3beOCT1wZvgiSANG0dKjjO", "uri": "spotify:track:3beOCT1wZvgiSANG0dKjjO", "track_href": "https://api.spotify.com/v1/tracks/3beOCT1wZvgiSANG0dKjjO", "analysis_url": "https://api.spotify.com/v1/audio-analysis/3beOCT1wZvgiSANG0dKjjO", "duration_ms": 236893, "time_signature": 4}, {"danceability": 0.385, "energy": 0.875, "key": 7, "loudness": -5.159, "mode": 0, "speechiness": 0.0517, "acousticness": 0.279, "instrumentalness": 0, "liveness": 0.418, "valence": 0.624, "tempo": 164.179, "type": "audio_features", "id": "1vEGaaP2GBezUKyFCVNL7L", "uri": "spotify:track:1vEGaaP2GBezUKyFCVNL7L", "track_href": "https://api.spotify.com/v1/tracks/1vEGaaP2GBezUKyFCVNL7L", "analysis_url": "https://api.spotify.com/v1/audio-analysis/1vEGaaP2GBezUKyFCVNL7L", "duration_ms": 311316, "time_signature": 4}, {"danceability": 0.6, "energy": 0.702, "key": 6, "loudness": -5.657, "mode": 0, "speechiness": 0.0618, "acousticness": 0.537, "instrumentalness": 0, "liveness": 0.469, "valence": 0.759, "tempo": 151.871, "type": "audio_features", "id": "6NGduXgHHF7ORyIu8vrRCW", "uri": "spotify:track:6NGduXgHHF7ORyIu8vrRCW", "track_href": "https://api.spotify.com/v1/tracks/6NGduXgHHF7ORyIu8vrRCW", "analysis_url": "https://api.spotify.com/v1/audio-analysis/6NGduXgHHF7ORyIu8vrRCW", "duration_ms": 220846, "time_signature": 4}, {"danceability": 0.658, "energy": 0.862, "key": 0, "loudness": -7.772, "mode": 1, "speechiness": 0.045, "acousticness": 0.397, "instrumentalness": 1.73e-05, "liveness": 0.852, "valence": 0.889, "tempo": 91.702, "type": "audio_features", "id": "1PWpeF2KQQzBjqkJPMqvpJ", "uri": "spotify:track:1PWpeF2KQQzBjqkJPMqvpJ", "track_href": "https://api.spotify.com/v1/tracks/1PWpeF2KQQzBjqkJPMqvpJ", "analysis_url": "https://api.spotify.com/v1/audio-analysis/1PWpeF2KQQzBjqkJPMqvpJ", "duration_ms": 233920, "time_signature": 4}, {"danceability": 0.62, "energy": 0.719, "key": 11, "loudness": -7.937, "mode": 0, "speechiness": 0.0697, "acousticness": 0.669, "instrumentalness": 0, "liveness": 0.934, "valence": 0.802, "tempo": 92.941, "type": "audio_features", "id": "3PLdcrfVesYKyTpS1EXsxO", "uri": "spotify:track:3PLdcrfVesYKyTpS1EXsxO", "track_href": "https://api.spotify.com/v1/tracks/3PLdcrfVesYKyTpS1EXsxO", "analysis_url": "https://api.spotify.com/v1/audio-analysis/3PLdcrfVesYKyTpS1EXsxO", "duration_ms": 163038, "time_signature": 4}, {"danceability": 0.715, "energy": 0.937, "key": 11, "loudness": -4.079, "mode": 0, "speechiness": 0.234, "acousticness": 0.476, "instrumentalness": 0, "liveness": 0.596, "valence": 0.859, "tempo": 167.059, "type": "audio_features", "id": "73wNiTvMxHKKon8sHBGv6J", "uri": "spotify:track:73wNiTvMxHKKon8sHBGv6J", "track_href": "https://api.spotify.com/v1/tracks/73wNiTvMxHKKon8sHBGv6J", "analysis_url": "https://api.spotify.com/v1/audio-analysis/73wNiTvMxHKKon8sHBGv6J", "duration_ms": 129093, "time_signature": 4}, {"danceability": 0.477, "energy": 0.813, "key": 10, "loudness": -5.919, "mode": 1, "speechiness": 0.0743, "acousticness": 0.605, "instrumentalness": 0, "liveness": 0.467, "valence": 0.75, "tempo": 97.888, "type": "audio_features", "id": "3rDAHk73LZmgJIyGZstWQ0", "uri": "spotify:track:3rDAHk73LZmgJIyGZstWQ0", "track_href": "https://api.spotify.com/v1/tracks/3rDAHk73LZmgJIyGZstWQ0", "analysis_url": "https://api.spotify.com/v1/audio-analysis/3rDAHk73LZmgJIyGZstWQ0", "duration_ms": 342622, "time_signature": 4}, {"danceability": 0.556, "energy": 0.714, "key": 11, "loudness": -5.973, "mode": 0, "speechiness": 0.0614, "acousticness": 0.452, "instrumentalness": 0, "liveness": 0.983, "valence": 0.696, "tempo": 147.57, "type": "audio_features", "id": "0ePqDlJvdIrs58EKvPb9hN", "uri": "spotify:track:0ePqDlJvdIrs58EKvPb9hN", "track_href": "https://api.spotify.com/v1/tracks/0ePqDlJvdIrs58EKvPb9hN", "analysis_url": "https://api.spotify.com/v1/audio-analysis/0ePqDlJvdIrs58EKvPb9hN", "duration_ms": 232279, "time_signature": 4}, {"danceability": 0.402, "energy": 0.845, "key": 2, "loudness": -7.592, "mode": 1, "speechiness": 0.0992, "acousticness": 0.219, "instrumentalness": 7.64e-06, "liveness": 0.399, "valence": 0.707, "tempo": 93.598, "type": "audio_features", "id": "2C9MNfyUehdQCxtuBJEnBI", "uri": "spotify:track:2C9MNfyUehdQCxtuBJEnBI", "track_href": "https://api.spotify.com/v1/tracks/2C9MNfyUehdQCxtuBJEnBI", "analysis_url": "https://api.spotify.com/v1/audio-analysis/2C9MNfyUehdQCxtuBJEnBI", "duration_ms": 200640, "time_signature": 4}, {"danceability": 0.669, "energy": 0.843, "key": 8, "loudness": -6.991, "mode": 1, "speechiness": 0.232, "acousticness": 0.587, "instrumentalness": 0, "liveness": 0.556, "valence": 0.559, "tempo": 148.942, "type": "audio_features", "id": "6CqDt0kMtPLvul13OS9afe", "uri": "spotify:track:6CqDt0kMtPLvul13OS9afe", "track_href": "https://api.spotify.com/v1/tracks/6CqDt0kMtPLvul13OS9afe", "analysis_url": "https://api.spotify.com/v1/audio-analysis/6CqDt0kMtPLvul13OS9afe", "duration_ms": 154165, "time_signature": 4}, {"danceability": 0.582, "energy": 0.617, "key": 5, "loudness": -9.098, "mode": 0, "speechiness": 0.0369, "acousticness": 0.18, "instrumentalness": 0, "liveness": 0.685, "valence": 0.569, "tempo": 143.852, "type": "audio_features", "id": "3wgj36suI9LOKN7HnftwJd", "uri": "spotify:track:3wgj36suI9LOKN7HnftwJd", "track_href": "https://api.spotify.com/v1/tracks/3wgj36suI9LOKN7HnftwJd", "analysis_url": "https://api.spotify.com/v1/audio-analysis/3wgj36suI9LOKN7HnftwJd", "duration_ms": 210333, "time_signature": 4}, {"danceability": 0.7, "energy": 0.903, "key": 2, "loudness": -7.022, "mode": 1, "speechiness": 0.0448, "acousticness": 0.511, "instrumentalness": 2.38e-05, "liveness": 0.957, "valence": 0.777, "tempo": 101.993, "type": "audio_features", "id": "20oJRGD2UinF4AHzIg1FSH", "uri": "spotify:track:20oJRGD2UinF4AHzIg1FSH", "track_href": "https://api.spotify.com/v1/tracks/20oJRGD2UinF4AHzIg1FSH", "analysis_url": "https://api.spotify.com/v1/audio-analysis/20oJRGD2UinF4AHzIg1FSH", "duration_ms": 246143, "time_signature": 4}, {"danceability": 0.476, "energy": 0.92, "key": 1, "loudness": -3.749, "mode": 0, "speechiness": 0.112, "acousticness": 0.26, "instrumentalness": 0, "liveness": 0.355, "valence": 0.613, "tempo": 168.127, "type": "audio_features", "id": "1Cm7BPymAPBOzKKXRoRHN4", "uri": "spotify:track:1Cm7BPymAPBOzKKXRoRHN4", "track_href": "https://api.spotify.com/v1/tracks/1Cm7BPymAPBOzKKXRoRHN4", "analysis_url": "https://api.spotify.com/v1/audio-analysis/1Cm7BPymAPBOzKKXRoRHN4", "duration_ms": 349445, "time_signature": 4}, {"danceability": 0.504, "energy": 0.826, "key": 8, "loudness": -4.916, "mode": 1, "speechiness": 0.253, "acousticness": 0.501, "instrumentalness": 0, "liveness": 0.62, "valence": 0.747, "tempo": 83.729, "type": "audio_features", "id": "1Wu5SAcCr9R4fH6aXbaD3E", "uri": "spotify:track:1Wu5SAcCr9R4fH6aXbaD3E", "track_href": "https://api.spotify.com/v1/tracks/1Wu5SAcCr9R4fH6aXbaD3E", "analysis_url": "https://api.spotify.com/v1/audio-analysis/1Wu5SAcCr9R4fH6aXbaD3E", "duration_ms": 158098, "time_signature": 4}, {"danceability": 0.649, "energy": 0.785, "key": 11, "loudness": -6.588, "mode": 0, "speechiness": 0.0347, "acousticness": 0.607, "instrumentalness": 0, "liveness": 0.797, "valence": 0.965, "tempo": 92.982, "type": "audio_features", "id": "50mawjudhEofTcUIpRmGXr", "uri": "spotify:track:50mawjudhEofTcUIpRmGXr", "track_href": "https://api.spotify.com/v1/tracks/50mawjudhEofTcUIpRmGXr", "analysis_url": "https://api.spotify.com/v1/audio-analysis/50mawjudhEofTcUIpRmGXr", "duration_ms": 246227, "time_signature": 4}, {"danceability": 0.648, "energy": 0.725, "key": 4, "loudness": -8.49, "mode": 0, "speechiness": 0.0475, "acousticness": 0.729, "instrumentalness": 1.81e-06, "liveness": 0.953, "valence": 0.808, "tempo": 96.19, "type": "audio_features", "id": "4Mnfug0sgaMw7g3wyZD4ss", "uri": "spotify:track:4Mnfug0sgaMw7g3wyZD4ss", "track_href": "https://api.spotify.com/v1/tracks/4Mnfug0sgaMw7g3wyZD4ss", "analysis_url": "https://api.spotify.com/v1/audio-analysis/4Mnfug0sgaMw7g3wyZD4ss", "duration_ms": 192078, "time_signature": 4}, {"danceability": 0.443, "energy": 0.729, "key": 7, "loudness": -9.089, "mode": 1, "speechiness": 0.0582, "acousticness": 0.584, "instrumentalness": 0, "liveness": 0.81, "valence": 0.529, "tempo": 145.606, "type": "audio_features", "id": "7Gjd4xF6dy3Qf5UvkpCEOU", "uri": "spotify:track:7Gjd4xF6dy3Qf5UvkpCEOU", "track_href": "https://api.spotify.com/v1/tracks/7Gjd4xF6dy3Qf5UvkpCEOU", "analysis_url": "https://api.spotify.com/v1/audio-analysis/7Gjd4xF6dy3Qf5UvkpCEOU", "duration_ms": 187880, "time_signature": 4}, {"danceability": 0.562, "energy": 0.716, "key": 4, "loudness": -7.316, "mode": 1, "speechiness": 0.0658, "acousticness": 0.384, "instrumentalness": 0, "liveness": 0.319, "valence": 0.42, "tempo": 148.075, "type": "audio_features", "id": "07BRm4ATW5VXnpUagfVJhs", "uri": "spotify:track:07BRm4ATW5VXnpUagfVJhs", "track_href": "https://api.spotify.com/v1/tracks/07BRm4ATW5VXnpUagfVJhs", "analysis_url": "https://api.spotify.com/v1/audio-analysis/07BRm4ATW5VXnpUagfVJhs", "duration_ms": 197027, "time_signature": 4}, {"danceability": 0.431, "energy": 0.711, "key": 8, "loudness": -8.503, "mode": 1, "speechiness": 0.0506, "acousticness": 0.695, "instrumentalness": 7.14e-05, "liveness": 0.836, "valence": 0.564, "tempo": 147.977, "type": "audio_features", "id": "42WLCUmWf69VGvk2Rzoj19", "uri": "spotify:track:42WLCUmWf69VGvk2Rzoj19", "track_href": "https://api.spotify.com/v1/tracks/42WLCUmWf69VGvk2Rzoj19", "analysis_url": "https://api.spotify.com/v1/audio-analysis/42WLCUmWf69VGvk2Rzoj19", "duration_ms": 307067, "time_signature": 4}, {"danceability": 0.53, "energy": 0.852, "key": 7, "loudness": -6.17, "mode": 0, "speechiness": 0.0537, "acousticness": 0.63, "instrumentalness": 0, "liveness": 0.359, "valence": 0.632, "tempo": 163.817, "type": "audio_features", "id": "1IrLBbDDzD7kamLfGqcj08", "uri": "spotify:track:1IrLBbDDzD7kamLfGqcj08", "track_href": "https://api.spotify.com/v1/tracks/1IrLBbDDzD7kamLfGqcj08", "analysis_url": "https://api.spotify.com/v1/audio-analysis/1IrLBbDDzD7kamLfGqcj08", "duration_ms": 121637, "time_signature": 4}, {"danceability": 0.624, "energy": 0.727, "key": 4, "loudness": -8.838, "mode": 1, "speechiness": 0.0617, "acousticness": 0.701, "instrumentalness": 0, "liveness": 0.865, "valence": 0.859, "tempo": 172.037, "type": "audio_features", "id": "3Hq8apYUWUe5VYF691TBbD", "uri": "spotify:track:3Hq8apYUWUe5VYF691TBbD", "track_href": "https://api.spotify.com/v1/tracks/3Hq8apYUWUe5VYF691TBbD", "analysis_url": "https://api.spotify.com/v1/audio-analysis/3Hq8apYUWUe5VYF691TBbD", "duration_ms": 192993, "time_signature": 4}, {"danceability": 0.624, "energy": 0.734, "key": 4, "loudness": -6.498, "mode": 0, "speechiness": 0.0475, "acousticness": 0.516, "instrumentalness": 0, "liveness": 0.828, "valence": 0.499, "tempo": 139.905, "type": "audio_features", "id": "65vJAh07BdwurqR9SRa6f8", "uri": "spotify:track:65vJAh07BdwurqR9SRa6f8", "track_href": "https://api.spotify.com/v1/tracks/65vJAh07BdwurqR9SRa6f8", "analysis_url": "https://api.spotify.com/v1/audio-analysis/65vJAh07BdwurqR9SRa6f8", "duration_ms": 198678, "time_signature": 4}, {"danceability": 0.515, "energy": 0.718, "key": 0, "loudness": -7.536, "mode": 1, "speechiness": 0.0683, "acousticness": 0.535, "instrumentalness": 0, "liveness": 0.671, "valence": 0.833, "tempo": 102.527, "type": "audio_features", "id": "2CU2o0jyWO8xq0TiJPXZ6y", "uri": "spotify:track:2CU2o0jyWO8xq0TiJPXZ6y", "track_href": "https://api.spotify.com/v1/tracks/2CU2o0jyWO8xq0TiJPXZ6y", "analysis_url": "https://api.spotify.com/v1/audio-analysis/2CU2o0jyWO8xq0TiJPXZ6y", "duration_ms": 326202, "time_signature": 4}, {"danceability": 0.412, "energy": 0.606, "key": 4, "loudness": -7.976, "mode": 0, "speechiness": 0.0415, "acousticness": 0.727, "instrumentalness": 0, "liveness": 0.946, "valence": 0.51, "tempo": 146.011, "type": "audio_features", "id": "1knPDCgi2UsdiPECvEXMIa", "uri": "spotify:track:1knPDCgi2UsdiPECvEXMIa", "track_href": "https://api.spotify.com/v1/tracks/1knPDCgi2UsdiPECvEXMIa", "analysis_url": "https://api.spotify.com/v1/audio-analysis/1knPDCgi2UsdiPECvEXMIa", "duration_ms": 167985, "time_signature": 4}, {"danceability": 0.513, "energy": 0.771, "key": 4, "loudness": -8.745, "mode": 0, "speechiness": 0.0722, "acousticness": 0.454, "instrumentalness": 0, "liveness": 0.946, "valence": 0.695, "tempo": 148.851, "type": "audio_features", "id": "6Ax6xhCxoCV2XkDl8TJitT", "uri": "spotify:track:6Ax6xhCxoCV2XkDl8TJitT", "track_href": "https://api.spotify.com/v1/tracks/6Ax6xhCxoCV2XkDl8TJitT", "analysis_url": "https://api.spotify.com/v1/audio-analysis/6Ax6xhCxoCV2XkDl8TJitT", "duration_ms": 248000, "time_signature": 4}, {"danceability": 0.385, "energy": 0.875, "key": 7, "loudness": -5.159, "mode": 0, "speechiness": 0.0517, "acousticness": 0.279, "instrumentalness": 0, "liveness": 0.418, "valence": 0.624, "tempo": 164.179, "type": "audio_features", "id": "1vEGaaP2GBezUKyFCVNL7L", "uri": "spotify:track:1vEGaaP2GBezUKyFCVNL7L", "track_href": "https://api.spotify.com/v1/tracks/1vEGaaP2GBezUKyFCVNL7L", "analysis_url": "https://api.spotify.com/v1/audio-analysis/1vEGaaP2GBezUKyFCVNL7L", "duration_ms": 311316, "time_signature": 4}, {"danceability": 0.565, "energy": 0.765, "key": 2, "loudness": -8.209, "mode": 1, "speechiness": 0.0417, "acousticness": 0.512, "instrumentalness": 1.48e-06, "liveness": 0.945, "valence": 0.806, "tempo": 160.052, "type": "audio_features", "id": "6VUn2TrpUNappitMnr0oFe", "uri": "spotify:track:6VUn2TrpUNappitMnr0oFe", "track_href": "https://api.spotify.com/v1/tracks/6VUn2TrpUNappitMnr0oFe", "analysis_url": "https://api.spotify.com/v1/audio-analysis/6VUn2TrpUNappitMnr0oFe", "duration_ms": 236697, "time_signature": 4}, {"danceability": 0.379, "energy": 0.805, "key": 6, "loudness": -6.233, "mode": 0, "speechiness": 0.0993, "acousticness": 0.352, "instrumentalness": 0, "liveness": 0.968, "valence": 0.722, "tempo": 157.094, "type": "audio_features", "id": "2Fj8K3IROlXO1xp6Y6Vtu2", "uri": "spotify:track:2Fj8K3IROlXO1xp6Y6Vtu2", "track_href": "https://api.spotify.com/v1/tracks/2Fj8K3IROlXO1xp6Y6Vtu2", "analysis_url": "https://api.spotify.com/v1/audio-analysis/2Fj8K3IROlXO1xp6Y6Vtu2", "duration_ms": 270427, "time_signature": 4}, {"danceability": 0.667, "energy": 0.647, "key": 10, "loudness": -9.173, "mode": 1, "speechiness": 0.0381, "acousticness": 0.524, "instrumentalness": 0, "liveness": 0.0613, "valence": 0.962, "tempo": 179.895, "type": "audio_features", "id": "0O9dWZhjnYjzPqqFpj4cTb", "uri": "spotify:track:0O9dWZhjnYjzPqqFpj4cTb", "track_href": "https://api.spotify.com/v1/tracks/0O9dWZhjnYjzPqqFpj4cTb", "analysis_url": "https://api.spotify.com/v1/audio-analysis/0O9dWZhjnYjzPqqFpj4cTb", "duration_ms": 194168, "time_signature": 4}, {"danceability": 0.609, "energy": 0.712, "key": 7, "loudness": -7.768, "mode": 0, "speechiness": 0.035, "acousticness": 0.838, "instrumentalness": 0, "liveness": 0.367, "valence": 0.623, "tempo": 148.042, "type": "audio_features", "id": "6i1tyRILrOSUB1VxlA7AiY", "uri": "spotify:track:6i1tyRILrOSUB1VxlA7AiY", "track_href": "https://api.spotify.com/v1/tracks/6i1tyRILrOSUB1VxlA7AiY", "analysis_url": "https://api.spotify.com/v1/audio-analysis/6i1tyRILrOSUB1VxlA7AiY", "duration_ms": 155786, "time_signature": 4}, {"danceability": 0.747, "energy": 0.67, "key": 8, "loudness": -7.563, "mode": 1, "speechiness": 0.0474, "acousticness": 0.691, "instrumentalness": 0, "liveness": 0.093, "valence": 0.769, "tempo": 96.096, "type": "audio_features", "id": "2DQrX3H6JavzYLtSACSKvL", "uri": "spotify:track:2DQrX3H6JavzYLtSACSKvL", "track_href": "https://api.spotify.com/v1/tracks/2DQrX3H6JavzYLtSACSKvL", "analysis_url": "https://api.spotify.com/v1/audio-analysis/2DQrX3H6JavzYLtSACSKvL", "duration_ms": 187848, "time_signature": 4}, {"danceability": 0.653, "energy": 0.931, "key": 10, "loudness": -5.569, "mode": 1, "speechiness": 0.0794, "acousticness": 0.593, "instrumentalness": 0, "liveness": 0.955, "valence": 0.579, "tempo": 95.982, "type": "audio_features", "id": "3flxltmjtskiHFIybmwAa7", "uri": "spotify:track:3flxltmjtskiHFIybmwAa7", "track_href": "https://api.spotify.com/v1/tracks/3flxltmjtskiHFIybmwAa7", "analysis_url": "https://api.spotify.com/v1/audio-analysis/3flxltmjtskiHFIybmwAa7", "duration_ms": 206813, "time_signature": 4}, {"danceability": 0.488, "energy": 0.505, "key": 1, "loudness": -8.852, "mode": 0, "speechiness": 0.0546, "acousticness": 0.125, "instrumentalness": 0, "liveness": 0.374, "valence": 0.163, "tempo": 147.542, "type": "audio_features", "id": "5pfjgNDp9KdQhpc6br5I4x", "uri": "spotify:track:5pfjgNDp9KdQhpc6br5I4x", "track_href": "https://api.spotify.com/v1/tracks/5pfjgNDp9KdQhpc6br5I4x", "analysis_url": "https://api.spotify.com/v1/audio-analysis/5pfjgNDp9KdQhpc6br5I4x", "duration_ms": 249240, "time_signature": 4}, {"danceability": 0.715, "energy": 0.937, "key": 11, "loudness": -4.079, "mode": 0, "speechiness": 0.234, "acousticness": 0.476, "instrumentalness": 0, "liveness": 0.596, "valence": 0.859, "tempo": 167.059, "type": "audio_features", "id": "73wNiTvMxHKKon8sHBGv6J", "uri": "spotify:track:73wNiTvMxHKKon8sHBGv6J", "track_href": "https://api.spotify.com/v1/tracks/73wNiTvMxHKKon8sHBGv6J", "analysis_url": "https://api.spotify.com/v1/audio-analysis/73wNiTvMxHKKon8sHBGv6J", "duration_ms": 129093, "time_signature": 4}, {"danceability": 0.607, "energy": 0.821, "key": 6, "loudness": -6.636, "mode": 1, "speechiness": 0.0486, "acousticness": 0.746, "instrumentalness": 0, "liveness": 0.95, "valence": 0.816, "tempo": 151.76, "type": "audio_features", "id": "7Bie9S1N5kujNYPafzotI4", "uri": "spotify:track:7Bie9S1N5kujNYPafzotI4", "track_href": "https://api.spotify.com/v1/tracks/7Bie9S1N5kujNYPafzotI4", "analysis_url": "https://api.spotify.com/v1/audio-analysis/7Bie9S1N5kujNYPafzotI4", "duration_ms": 205430, "time_signature": 4}, {"danceability": 0.624, "energy": 0.734, "key": 4, "loudness": -6.498, "mode": 0, "speechiness": 0.0475, "acousticness": 0.516, "instrumentalness": 0, "liveness": 0.828, "valence": 0.499, "tempo": 139.905, "type": "audio_features", "id": "65vJAh07BdwurqR9SRa6f8", "uri": "spotify:track:65vJAh07BdwurqR9SRa6f8", "track_href": "https://api.spotify.com/v1/tracks/65vJAh07BdwurqR9SRa6f8", "analysis_url": "https://api.spotify.com/v1/audio-analysis/65vJAh07BdwurqR9SRa6f8", "duration_ms": 198678, "time_signature": 4}, {"danceability": 0.688, "energy": 0.871, "key": 7, "loudness": -7.041, "mode": 1, "speechiness": 0.0571, "acousticness": 0.807, "instrumentalness": 0, "liveness": 0.953, "valence": 0.945, "tempo": 91.534, "type": "audio_features", "id": "3CY0WXRyNWkS3xfZuF4q1I", "uri": "spotify:track:3CY0WXRyNWkS3xfZuF4q1I", "track_href": "https://api.spotify.com/v1/tracks/3CY0WXRyNWkS3xfZuF4q1I", "analysis_url": "https://api.spotify.com/v1/audio-analysis/3CY0WXRyNWkS3xfZuF4q1I", "duration_ms": 195240, "time_signature": 4}, {"danceability": 0.657, "energy": 0.56, "key": 0, "loudness": -8.521, "mode": 1, "speechiness": 0.0331, "acousticness": 0.751, "instrumentalness": 0, "liveness": 0.0884, "valence": 0.728, "tempo": 135.956, "type": "audio_features", "id": "37nlL8SBx70ZVuiD7BfkwN", "uri": "spotify:track:37nlL8SBx70ZVuiD7BfkwN", "track_href": "https://api.spotify.com/v1/tracks/37nlL8SBx70ZVuiD7BfkwN", "analysis_url": "https://api.spotify.com/v1/audio-analysis/37nlL8SBx70ZVuiD7BfkwN", "duration_ms": 170455, "time_signature": 4}, {"danceability": 0.578, "energy": 0.769, "key": 1, "loudness": -5.339, "mode": 1, "speechiness": 0.039, "acousticness": 0.678, "instrumentalness": 0, "liveness": 0.467, "valence": 0.817, "tempo": 155.937, "type": "audio_features", "id": "1kWcd9h9HoeXsKaDVhSOtj", "uri": "spotify:track:1kWcd9h9HoeXsKaDVhSOtj", "track_href": "https://api.spotify.com/v1/tracks/1kWcd9h9HoeXsKaDVhSOtj", "analysis_url": "https://api.spotify.com/v1/audio-analysis/1kWcd9h9HoeXsKaDVhSOtj", "duration_ms": 196988, "time_signature": 4}, {"danceability": 0.593, "energy": 0.351, "key": 7, "loudness": -23.852, "mode": 1, "speechiness": 0.0518, "acousticness": 0.407, "instrumentalness": 0, "liveness": 0.932, "valence": 0.711, "tempo": 101.966, "type": "audio_features", "id": "7A7WraHA4SXB7ScKyapAEI", "uri": "spotify:track:7A7WraHA4SXB7ScKyapAEI", "track_href": "https://api.spotify.com/v1/tracks/7A7WraHA4SXB7ScKyapAEI", "analysis_url": "https://api.spotify.com/v1/audio-analysis/7A7WraHA4SXB7ScKyapAEI", "duration_ms": 181120, "time_signature": 4}, {"danceability": 0.658, "energy": 0.818, "key": 2, "loudness": -7.969, "mode": 1, "speechiness": 0.0349, "acousticness": 0.398, "instrumentalness": 0, "liveness": 0.929, "valence": 0.939, "tempo": 92.086, "type": "audio_features", "id": "2R6PIzBpnZPpAzXbGxAmqq", "uri": "spotify:track:2R6PIzBpnZPpAzXbGxAmqq", "track_href": "https://api.spotify.com/v1/tracks/2R6PIzBpnZPpAzXbGxAmqq", "analysis_url": "https://api.spotify.com/v1/audio-analysis/2R6PIzBpnZPpAzXbGxAmqq", "duration_ms": 204267, "time_signature": 4}, {"danceability": 0.455, "energy": 0.888, "key": 11, "loudness": -7.744, "mode": 1, "speechiness": 0.0763, "acousticness": 0.194, "instrumentalness": 1.86e-05, "liveness": 0.764, "valence": 0.593, "tempo": 104.919, "type": "audio_features", "id": "1JISGjYOQoiJe6xc7CWnQo", "uri": "spotify:track:1JISGjYOQoiJe6xc7CWnQo", "track_href": "https://api.spotify.com/v1/tracks/1JISGjYOQoiJe6xc7CWnQo", "analysis_url": "https://api.spotify.com/v1/audio-analysis/1JISGjYOQoiJe6xc7CWnQo", "duration_ms": 206920, "time_signature": 4}, {"danceability": 0.471, "energy": 0.757, "key": 9, "loudness": -8.649, "mode": 1, "speechiness": 0.0521, "acousticness": 0.613, "instrumentalness": 0, "liveness": 0.92, "valence": 0.797, "tempo": 156.498, "type": "audio_features", "id": "7MBh48plnAaScSLDKNLZSd", "uri": "spotify:track:7MBh48plnAaScSLDKNLZSd", "track_href": "https://api.spotify.com/v1/tracks/7MBh48plnAaScSLDKNLZSd", "analysis_url": "https://api.spotify.com/v1/audio-analysis/7MBh48plnAaScSLDKNLZSd", "duration_ms": 253400, "time_signature": 4}, {"danceability": 0.719, "energy": 0.953, "key": 5, "loudness": -4.89, "mode": 0, "speechiness": 0.0527, "acousticness": 0.566, "instrumentalness": 8.28e-06, "liveness": 0.659, "valence": 0.725, "tempo": 109.001, "type": "audio_features", "id": "7ezk6Fzan6hPpT6XqiJNWS", "uri": "spotify:track:7ezk6Fzan6hPpT6XqiJNWS", "track_href": "https://api.spotify.com/v1/tracks/7ezk6Fzan6hPpT6XqiJNWS", "analysis_url": "https://api.spotify.com/v1/audio-analysis/7ezk6Fzan6hPpT6XqiJNWS", "duration_ms": 190400, "time_signature": 4}, {"danceability": 0.542, "energy": 0.69, "key": 2, "loudness": -8.344, "mode": 1, "speechiness": 0.0851, "acousticness": 0.391, "instrumentalness": 0, "liveness": 0.56, "valence": 0.783, "tempo": 119.104, "type": "audio_features", "id": "4Wyz99l6GOJwRfgqrY0M9g", "uri": "spotify:track:4Wyz99l6GOJwRfgqrY0M9g", "track_href": "https://api.spotify.com/v1/tracks/4Wyz99l6GOJwRfgqrY0M9g", "analysis_url": "https://api.spotify.com/v1/audio-analysis/4Wyz99l6GOJwRfgqrY0M9g", "duration_ms": 214600, "time_signature": 4}, {"danceability": 0.54, "energy": 0.71, "key": 7, "loudness": -6.091, "mode": 1, "speechiness": 0.039, "acousticness": 0.686, "instrumentalness": 0, "liveness": 0.628, "valence": 0.822, "tempo": 162.019, "type": "audio_features", "id": "06WkQibI8OhOLjDxIRKu5B", "uri": "spotify:track:06WkQibI8OhOLjDxIRKu5B", "track_href": "https://api.spotify.com/v1/tracks/06WkQibI8OhOLjDxIRKu5B", "analysis_url": "https://api.spotify.com/v1/audio-analysis/06WkQibI8OhOLjDxIRKu5B", "duration_ms": 345053, "time_signature": 4}, {"danceability": 0.604, "energy": 0.842, "key": 0, "loudness": -8.481, "mode": 1, "speechiness": 0.0472, "acousticness": 0.149, "instrumentalness": 0, "liveness": 0.568, "valence": 0.504, "tempo": 103.71, "type": "audio_features", "id": "1DwVWibPBDTBNLCuzV4QlU", "uri": "spotify:track:1DwVWibPBDTBNLCuzV4QlU", "track_href": "https://api.spotify.com/v1/tracks/1DwVWibPBDTBNLCuzV4QlU", "analysis_url": "https://api.spotify.com/v1/audio-analysis/1DwVWibPBDTBNLCuzV4QlU", "duration_ms": 175280, "time_signature": 4}, {"danceability": 0.385, "energy": 0.875, "key": 7, "loudness": -5.159, "mode": 0, "speechiness": 0.0517, "acousticness": 0.279, "instrumentalness": 0, "liveness": 0.418, "valence": 0.624, "tempo": 164.179, "type": "audio_features", "id": "1vEGaaP2GBezUKyFCVNL7L", "uri": "spotify:track:1vEGaaP2GBezUKyFCVNL7L", "track_href": "https://api.spotify.com/v1/tracks/1vEGaaP2GBezUKyFCVNL7L", "analysis_url": "https://api.spotify.com/v1/audio-analysis/1vEGaaP2GBezUKyFCVNL7L", "duration_ms": 311316, "time_signature": 4}, {"danceability": 0.43, "energy": 0.898, "key": 5, "loudness": -5.537, "mode": 1, "speechiness": 0.0477, "acousticness": 0.372, "instrumentalness": 0, "liveness": 0.901, "valence": 0.776, "tempo": 104.529, "type": "audio_features", "id": "3PkqPpAdMMhAfsxITFJpha", "uri": "spotify:track:3PkqPpAdMMhAfsxITFJpha", "track_href": "https://api.spotify.com/v1/tracks/3PkqPpAdMMhAfsxITFJpha", "analysis_url": "https://api.spotify.com/v1/audio-analysis/3PkqPpAdMMhAfsxITFJpha", "duration_ms": 272912, "time_signature": 4}, {"danceability": 0.645, "energy": 0.726, "key": 2, "loudness": -7.926, "mode": 1, "speechiness": 0.0675, "acousticness": 0.611, "instrumentalness": 0, "liveness": 0.877, "valence": 0.838, "tempo": 95.517, "type": "audio_features", "id": "1oXFfHuBuasMQ9lnPSRvGU", "uri": "spotify:track:1oXFfHuBuasMQ9lnPSRvGU", "track_href": "https://api.spotify.com/v1/tracks/1oXFfHuBuasMQ9lnPSRvGU", "analysis_url": "https://api.spotify.com/v1/audio-analysis/1oXFfHuBuasMQ9lnPSRvGU", "duration_ms": 188133, "time_signature": 4}, {"danceability": 0.611, "energy": 0.735, "key": 7, "loudness": -8.372, "mode": 0, "speechiness": 0.0345, "acousticness": 0.257, "instrumentalness": 0, "liveness": 0.914, "valence": 0.832, "tempo": 88.013, "type": "audio_features", "id": "6XOsXDAtgNGOPzyalU4zcT", "uri": "spotify:track:6XOsXDAtgNGOPzyalU4zcT", "track_href": "https://api.spotify.com/v1/tracks/6XOsXDAtgNGOPzyalU4zcT", "analysis_url": "https://api.spotify.com/v1/audio-analysis/6XOsXDAtgNGOPzyalU4zcT", "duration_ms": 221213, "time_signature": 4}, {"danceability": 0.491, "energy": 0.83, "key": 11, "loudness": -6.022, "mode": 1, "speechiness": 0.167, "acousticness": 0.354, "instrumentalness": 0, "liveness": 0.956, "valence": 0.512, "tempo": 159.272, "type": "audio_features", "id": "4BVH1mjLoS0TeJ0ni2o9AN", "uri": "spotify:track:4BVH1mjLoS0TeJ0ni2o9AN", "track_href": "https://api.spotify.com/v1/tracks/4BVH1mjLoS0TeJ0ni2o9AN", "analysis_url": "https://api.spotify.com/v1/audio-analysis/4BVH1mjLoS0TeJ0ni2o9AN", "duration_ms": 218400, "time_signature": 4}, {"danceability": 0.427, "energy": 0.823, "key": 0, "loudness": -9.747, "mode": 1, "speechiness": 0.0539, "acousticness": 0.236, "instrumentalness": 3.46e-05, "liveness": 0.949, "valence": 0.699, "tempo": 160.111, "type": "audio_features", "id": "6QdZ5mPfq42MkLoXxX4E2x", "uri": "spotify:track:6QdZ5mPfq42MkLoXxX4E2x", "track_href": "https://api.spotify.com/v1/tracks/6QdZ5mPfq42MkLoXxX4E2x", "analysis_url": "https://api.spotify.com/v1/audio-analysis/6QdZ5mPfq42MkLoXxX4E2x", "duration_ms": 208040, "time_signature": 4}, {"danceability": 0.715, "energy": 0.937, "key": 11, "loudness": -4.079, "mode": 0, "speechiness": 0.234, "acousticness": 0.476, "instrumentalness": 0, "liveness": 0.596, "valence": 0.859, "tempo": 167.059, "type": "audio_features", "id": "73wNiTvMxHKKon8sHBGv6J", "uri": "spotify:track:73wNiTvMxHKKon8sHBGv6J", "track_href": "https://api.spotify.com/v1/tracks/73wNiTvMxHKKon8sHBGv6J", "analysis_url": "https://api.spotify.com/v1/audio-analysis/73wNiTvMxHKKon8sHBGv6J", "duration_ms": 129093, "time_signature": 4}, {"danceability": 0.689, "energy": 0.812, "key": 7, "loudness": -6.79, "mode": 1, "speechiness": 0.0412, "acousticness": 0.616, "instrumentalness": 3.56e-05, "liveness": 0.88, "valence": 0.888, "tempo": 98.142, "type": "audio_features", "id": "7KbrWtA4XzdC1jsGp85Wve", "uri": "spotify:track:7KbrWtA4XzdC1jsGp85Wve", "track_href": "https://api.spotify.com/v1/tracks/7KbrWtA4XzdC1jsGp85Wve", "analysis_url": "https://api.spotify.com/v1/audio-analysis/7KbrWtA4XzdC1jsGp85Wve", "duration_ms": 297394, "time_signature": 4}, {"danceability": 0.323, "energy": 0.655, "key": 0, "loudness": -7.412, "mode": 1, "speechiness": 0.0375, "acousticness": 0.676, "instrumentalness": 0, "liveness": 0.767, "valence": 0.657, "tempo": 164.77, "type": "audio_features", "id": "40ejYprsOG1G7RwuOcRyxo", "uri": "spotify:track:40ejYprsOG1G7RwuOcRyxo", "track_href": "https://api.spotify.com/v1/tracks/40ejYprsOG1G7RwuOcRyxo", "analysis_url": "https://api.spotify.com/v1/audio-analysis/40ejYprsOG1G7RwuOcRyxo", "duration_ms": 268240, "time_signature": 4}, {"danceability": 0.507, "energy": 0.818, "key": 1, "loudness": -7.535, "mode": 0, "speechiness": 0.1, "acousticness": 0.804, "instrumentalness": 0, "liveness": 0.976, "valence": 0.762, "tempo": 128.512, "type": "audio_features", "id": "4YwjGd3CwzBiuulNuzcNff", "uri": "spotify:track:4YwjGd3CwzBiuulNuzcNff", "track_href": "https://api.spotify.com/v1/tracks/4YwjGd3CwzBiuulNuzcNff", "analysis_url": "https://api.spotify.com/v1/audio-analysis/4YwjGd3CwzBiuulNuzcNff", "duration_ms": 171160, "time_signature": 4}, {"danceability": 0.656, "energy": 0.817, "key": 9, "loudness": -7.572, "mode": 0, "speechiness": 0.0405, "acousticness": 0.618, "instrumentalness": 7.71e-06, "liveness": 0.95, "valence": 0.96, "tempo": 92.788, "type": "audio_features", "id": "0UBgbxwL6ZHjR7F6fjFpBI", "uri": "spotify:track:0UBgbxwL6ZHjR7F6fjFpBI", "track_href": "https://api.spotify.com/v1/tracks/0UBgbxwL6ZHjR7F6fjFpBI", "analysis_url": "https://api.spotify.com/v1/audio-analysis/0UBgbxwL6ZHjR7F6fjFpBI", "duration_ms": 198800, "time_signature": 4}, {"danceability": 0.552, "energy": 0.746, "key": 2, "loudness": -8.293, "mode": 1, "speechiness": 0.0537, "acousticness": 0.722, "instrumentalness": 1.25e-06, "liveness": 0.979, "valence": 0.769, "tempo": 93.888, "type": "audio_features", "id": "675sZZfbv7A3S8EukDCW7l", "uri": "spotify:track:675sZZfbv7A3S8EukDCW7l", "track_href": "https://api.spotify.com/v1/tracks/675sZZfbv7A3S8EukDCW7l", "analysis_url": "https://api.spotify.com/v1/audio-analysis/675sZZfbv7A3S8EukDCW7l", "duration_ms": 321597, "time_signature": 4}, {"danceability": 0.565, "energy": 0.672, "key": 0, "loudness": -6.685, "mode": 0, "speechiness": 0.0487, "acousticness": 0.679, "instrumentalness": 0, "liveness": 0.467, "valence": 0.868, "tempo": 159.811, "type": "audio_features", "id": "1obU3i5Y9bnntO0vs80IRh", "uri": "spotify:track:1obU3i5Y9bnntO0vs80IRh", "track_href": "https://api.spotify.com/v1/tracks/1obU3i5Y9bnntO0vs80IRh", "analysis_url": "https://api.spotify.com/v1/audio-analysis/1obU3i5Y9bnntO0vs80IRh", "duration_ms": 175425, "time_signature": 4}, {"danceability": 0.52, "energy": 0.699, "key": 0, "loudness": -8.951, "mode": 1, "speechiness": 0.0493, "acousticness": 0.458, "instrumentalness": 2e-06, "liveness": 0.964, "valence": 0.688, "tempo": 150.42, "type": "audio_features", "id": "4MJm8JudMDPBqZgP69rE78", "uri": "spotify:track:4MJm8JudMDPBqZgP69rE78", "track_href": "https://api.spotify.com/v1/tracks/4MJm8JudMDPBqZgP69rE78", "analysis_url": "https://api.spotify.com/v1/audio-analysis/4MJm8JudMDPBqZgP69rE78", "duration_ms": 256960, "time_signature": 4}, {"danceability": 0.693, "energy": 0.684, "key": 11, "loudness": -7.819, "mode": 1, "speechiness": 0.032, "acousticness": 0.803, "instrumentalness": 7.11e-05, "liveness": 0.148, "valence": 0.835, "tempo": 143.907, "type": "audio_features", "id": "1Oz1DVKz7G7gbuZJ0XJbNx", "uri": "spotify:track:1Oz1DVKz7G7gbuZJ0XJbNx", "track_href": "https://api.spotify.com/v1/tracks/1Oz1DVKz7G7gbuZJ0XJbNx", "analysis_url": "https://api.spotify.com/v1/audio-analysis/1Oz1DVKz7G7gbuZJ0XJbNx", "duration_ms": 179925, "time_signature": 4}, {"danceability": 0.691, "energy": 0.752, "key": 4, "loudness": -6.796, "mode": 0, "speechiness": 0.157, "acousticness": 0.708, "instrumentalness": 6.07e-06, "liveness": 0.912, "valence": 0.684, "tempo": 167.073, "type": "audio_features", "id": "1Yn7WrCiF8HizFK7lojTvi", "uri": "spotify:track:1Yn7WrCiF8HizFK7lojTvi", "track_href": "https://api.spotify.com/v1/tracks/1Yn7WrCiF8HizFK7lojTvi", "analysis_url": "https://api.spotify.com/v1/audio-analysis/1Yn7WrCiF8HizFK7lojTvi", "duration_ms": 159323, "time_signature": 4}, {"danceability": 0.429, "energy": 0.854, "key": 7, "loudness": -11.23, "mode": 0, "speechiness": 0.0453, "acousticness": 0.272, "instrumentalness": 0.000151, "liveness": 0.943, "valence": 0.783, "tempo": 165.09, "type": "audio_features", "id": "4JmJWZKDe224LwO5m73rPs", "uri": "spotify:track:4JmJWZKDe224LwO5m73rPs", "track_href": "https://api.spotify.com/v1/tracks/4JmJWZKDe224LwO5m73rPs", "analysis_url": "https://api.spotify.com/v1/audio-analysis/4JmJWZKDe224LwO5m73rPs", "duration_ms": 261428, "time_signature": 4}, {"danceability": 0.578, "energy": 0.79, "key": 9, "loudness": -7.84, "mode": 1, "speechiness": 0.0734, "acousticness": 0.827, "instrumentalness": 0, "liveness": 0.973, "valence": 0.781, "tempo": 90.276, "type": "audio_features", "id": "3kqzSZdgPRqMqgTvyw0V3t", "uri": "spotify:track:3kqzSZdgPRqMqgTvyw0V3t", "track_href": "https://api.spotify.com/v1/tracks/3kqzSZdgPRqMqgTvyw0V3t", "analysis_url": "https://api.spotify.com/v1/audio-analysis/3kqzSZdgPRqMqgTvyw0V3t", "duration_ms": 180880, "time_signature": 4}, {"danceability": 0.631, "energy": 0.799, "key": 2, "loudness": -7.183, "mode": 1, "speechiness": 0.0353, "acousticness": 0.241, "instrumentalness": 0, "liveness": 0.962, "valence": 0.84, "tempo": 100.444, "type": "audio_features", "id": "3G16ZnoxD6lmFIpWfYAPpc", "uri": "spotify:track:3G16ZnoxD6lmFIpWfYAPpc", "track_href": "https://api.spotify.com/v1/tracks/3G16ZnoxD6lmFIpWfYAPpc", "analysis_url": "https://api.spotify.com/v1/audio-analysis/3G16ZnoxD6lmFIpWfYAPpc", "duration_ms": 171413, "time_signature": 4}, {"danceability": 0.486, "energy": 0.774, "key": 0, "loudness": -8.95, "mode": 1, "speechiness": 0.101, "acousticness": 0.539, "instrumentalness": 0, "liveness": 0.941, "valence": 0.78, "tempo": 83.26, "type": "audio_features", "id": "65ZJCO6yTbxqU98xXJhEHT", "uri": "spotify:track:65ZJCO6yTbxqU98xXJhEHT", "track_href": "https://api.spotify.com/v1/tracks/65ZJCO6yTbxqU98xXJhEHT", "analysis_url": "https://api.spotify.com/v1/audio-analysis/65ZJCO6yTbxqU98xXJhEHT", "duration_ms": 162880, "time_signature": 4}, {"danceability": 0.563, "energy": 0.91, "key": 7, "loudness": -7.011, "mode": 1, "speechiness": 0.0445, "acousticness": 0.465, "instrumentalness": 0, "liveness": 0.185, "valence": 0.919, "tempo": 164.954, "type": "audio_features", "id": "0PrIQ0FKApOrDPJgkYMumJ", "uri": "spotify:track:0PrIQ0FKApOrDPJgkYMumJ", "track_href": "https://api.spotify.com/v1/tracks/0PrIQ0FKApOrDPJgkYMumJ", "analysis_url": "https://api.spotify.com/v1/audio-analysis/0PrIQ0FKApOrDPJgkYMumJ", "duration_ms": 182377, "time_signature": 4}, {"danceability": 0.429, "energy": 0.657, "key": 6, "loudness": -9.155, "mode": 0, "speechiness": 0.121, "acousticness": 0.518, "instrumentalness": 0, "liveness": 0.937, "valence": 0.493, "tempo": 87.189, "type": "audio_features", "id": "0zvQ9pOQUeWYYp6uy7uvX7", "uri": "spotify:track:0zvQ9pOQUeWYYp6uy7uvX7", "track_href": "https://api.spotify.com/v1/tracks/0zvQ9pOQUeWYYp6uy7uvX7", "analysis_url": "https://api.spotify.com/v1/audio-analysis/0zvQ9pOQUeWYYp6uy7uvX7", "duration_ms": 231467, "time_signature": 4}, {"danceability": 0.548, "energy": 0.643, "key": 9, "loudness": -6.57, "mode": 1, "speechiness": 0.0416, "acousticness": 0.746, "instrumentalness": 0, "liveness": 0.961, "valence": 0.668, "tempo": 143.929, "type": "audio_features", "id": "3eWHUE5D5R19q7BvOX7NSJ", "uri": "spotify:track:3eWHUE5D5R19q7BvOX7NSJ", "track_href": "https://api.spotify.com/v1/tracks/3eWHUE5D5R19q7BvOX7NSJ", "analysis_url": "https://api.spotify.com/v1/audio-analysis/3eWHUE5D5R19q7BvOX7NSJ", "duration_ms": 204681, "time_signature": 4}, {"danceability": 0.513, "energy": 0.771, "key": 4, "loudness": -8.745, "mode": 0, "speechiness": 0.0722, "acousticness": 0.454, "instrumentalness": 0, "liveness": 0.946, "valence": 0.695, "tempo": 148.851, "type": "audio_features", "id": "6Ax6xhCxoCV2XkDl8TJitT", "uri": "spotify:track:6Ax6xhCxoCV2XkDl8TJitT", "track_href": "https://api.spotify.com/v1/tracks/6Ax6xhCxoCV2XkDl8TJitT", "analysis_url": "https://api.spotify.com/v1/audio-analysis/6Ax6xhCxoCV2XkDl8TJitT", "duration_ms": 248000, "time_signature": 4}, {"danceability": 0.479, "energy": 0.661, "key": 9, "loudness": -9.204, "mode": 1, "speechiness": 0.0322, "acousticness": 0.54, "instrumentalness": 0, "liveness": 0.802, "valence": 0.79, "tempo": 165.717, "type": "audio_features", "id": "3cbrh44Z2UcVww435levjH", "uri": "spotify:track:3cbrh44Z2UcVww435levjH", "track_href": "https://api.spotify.com/v1/tracks/3cbrh44Z2UcVww435levjH", "analysis_url": "https://api.spotify.com/v1/audio-analysis/3cbrh44Z2UcVww435levjH", "duration_ms": 225413, "time_signature": 4}, {"danceability": 0.599, "energy": 0.812, "key": 11, "loudness": -5.749, "mode": 0, "speechiness": 0.0532, "acousticness": 0.732, "instrumentalness": 0, "liveness": 0.868, "valence": 0.716, "tempo": 96.049, "type": "audio_features", "id": "5sudtP2ME6aIHN20glKW0k", "uri": "spotify:track:5sudtP2ME6aIHN20glKW0k", "track_href": "https://api.spotify.com/v1/tracks/5sudtP2ME6aIHN20glKW0k", "analysis_url": "https://api.spotify.com/v1/audio-analysis/5sudtP2ME6aIHN20glKW0k", "duration_ms": 173587, "time_signature": 4}, {"danceability": 0.606, "energy": 0.775, "key": 8, "loudness": -8.396, "mode": 0, "speechiness": 0.118, "acousticness": 0.549, "instrumentalness": 0, "liveness": 0.718, "valence": 0.734, "tempo": 87.9, "type": "audio_features", "id": "0JcylAi4aaQl6nveHHVjPv", "uri": "spotify:track:0JcylAi4aaQl6nveHHVjPv", "track_href": "https://api.spotify.com/v1/tracks/0JcylAi4aaQl6nveHHVjPv", "analysis_url": "https://api.spotify.com/v1/audio-analysis/0JcylAi4aaQl6nveHHVjPv", "duration_ms": 185133, "time_signature": 4}, {"danceability": 0.557, "energy": 0.567, "key": 10, "loudness": -9.258, "mode": 0, "speechiness": 0.0352, "acousticness": 0.29, "instrumentalness": 0, "liveness": 0.713, "valence": 0.45, "tempo": 139.875, "type": "audio_features", "id": "4GRMdnstBK7NuXzEPajt7D", "uri": "spotify:track:4GRMdnstBK7NuXzEPajt7D", "track_href": "https://api.spotify.com/v1/tracks/4GRMdnstBK7NuXzEPajt7D", "analysis_url": "https://api.spotify.com/v1/audio-analysis/4GRMdnstBK7NuXzEPajt7D", "duration_ms": 259733, "time_signature": 4}, {"danceability": 0.57, "energy": 0.793, "key": 7, "loudness": -8.17, "mode": 1, "speechiness": 0.0546, "acousticness": 0.745, "instrumentalness": 0, "liveness": 0.834, "valence": 0.607, "tempo": 86.884, "type": "audio_features", "id": "6juqPdgEKpwNjoFyclr6b3", "uri": "spotify:track:6juqPdgEKpwNjoFyclr6b3", "track_href": "https://api.spotify.com/v1/tracks/6juqPdgEKpwNjoFyclr6b3", "analysis_url": "https://api.spotify.com/v1/audio-analysis/6juqPdgEKpwNjoFyclr6b3", "duration_ms": 179747, "time_signature": 4}, {"danceability": 0.383, "energy": 0.783, "key": 8, "loudness": -8.126, "mode": 1, "speechiness": 0.0709, "acousticness": 0.673, "instrumentalness": 0, "liveness": 0.944, "valence": 0.563, "tempo": 70.936, "type": "audio_features", "id": "6PH5tLQMmQMLflXqrP4vIu", "uri": "spotify:track:6PH5tLQMmQMLflXqrP4vIu", "track_href": "https://api.spotify.com/v1/tracks/6PH5tLQMmQMLflXqrP4vIu", "analysis_url": "https://api.spotify.com/v1/audio-analysis/6PH5tLQMmQMLflXqrP4vIu", "duration_ms": 235707, "time_signature": 4}, {"danceability": 0.502, "energy": 0.658, "key": 7, "loudness": -8.954, "mode": 1, "speechiness": 0.0465, "acousticness": 0.0911, "instrumentalness": 2.01e-06, "liveness": 0.93, "valence": 0.49, "tempo": 83.758, "type": "audio_features", "id": "2MhY90bXu49lH9T1uj7h0I", "uri": "spotify:track:2MhY90bXu49lH9T1uj7h0I", "track_href": "https://api.spotify.com/v1/tracks/2MhY90bXu49lH9T1uj7h0I", "analysis_url": "https://api.spotify.com/v1/audio-analysis/2MhY90bXu49lH9T1uj7h0I", "duration_ms": 224960, "time_signature": 4}, {"danceability": 0.583, "energy": 0.715, "key": 7, "loudness": -7.171, "mode": 1, "speechiness": 0.0377, "acousticness": 0.789, "instrumentalness": 0, "liveness": 0.475, "valence": 0.621, "tempo": 159.964, "type": "audio_features", "id": "4uc91u8VkgMjD71ifQKGJ8", "uri": "spotify:track:4uc91u8VkgMjD71ifQKGJ8", "track_href": "https://api.spotify.com/v1/tracks/4uc91u8VkgMjD71ifQKGJ8", "analysis_url": "https://api.spotify.com/v1/audio-analysis/4uc91u8VkgMjD71ifQKGJ8", "duration_ms": 199888, "time_signature": 4}, {"danceability": 0.497, "energy": 0.861, "key": 2, "loudness": -4.317, "mode": 1, "speechiness": 0.0423, "acousticness": 0.614, "instrumentalness": 0, "liveness": 0.325, "valence": 0.482, "tempo": 157.996, "type": "audio_features", "id": "7vT2iRW7l40p9fHnZHBkxy", "uri": "spotify:track:7vT2iRW7l40p9fHnZHBkxy", "track_href": "https://api.spotify.com/v1/tracks/7vT2iRW7l40p9fHnZHBkxy", "analysis_url": "https://api.spotify.com/v1/audio-analysis/7vT2iRW7l40p9fHnZHBkxy", "duration_ms": 224226, "time_signature": 4}, {"danceability": 0.581, "energy": 0.912, "key": 9, "loudness": -3.392, "mode": 1, "speechiness": 0.037, "acousticness": 0.367, "instrumentalness": 0, "liveness": 0.0766, "valence": 0.824, "tempo": 172.014, "type": "audio_features", "id": "6rPNEBrXXdLBFFunLctAI8", "uri": "spotify:track:6rPNEBrXXdLBFFunLctAI8", "track_href": "https://api.spotify.com/v1/tracks/6rPNEBrXXdLBFFunLctAI8", "analysis_url": "https://api.spotify.com/v1/audio-analysis/6rPNEBrXXdLBFFunLctAI8", "duration_ms": 213667, "time_signature": 4}, {"danceability": 0.551, "energy": 0.678, "key": 7, "loudness": -6.806, "mode": 1, "speechiness": 0.0552, "acousticness": 0.681, "instrumentalness": 0, "liveness": 0.246, "valence": 0.612, "tempo": 152.087, "type": "audio_features", "id": "1M9JZXjz6GCUH7VbFFBmJx", "uri": "spotify:track:1M9JZXjz6GCUH7VbFFBmJx", "track_href": "https://api.spotify.com/v1/tracks/1M9JZXjz6GCUH7VbFFBmJx", "analysis_url": "https://api.spotify.com/v1/audio-analysis/1M9JZXjz6GCUH7VbFFBmJx", "duration_ms": 186228, "time_signature": 4}, {"danceability": 0.571, "energy": 0.746, "key": 7, "loudness": -6.524, "mode": 1, "speechiness": 0.034, "acousticness": 0.744, "instrumentalness": 0, "liveness": 0.846, "valence": 0.809, "tempo": 81.973, "type": "audio_features", "id": "0j1syF5BFSty3vFoaj0vsX", "uri": "spotify:track:0j1syF5BFSty3vFoaj0vsX", "track_href": "https://api.spotify.com/v1/tracks/0j1syF5BFSty3vFoaj0vsX", "analysis_url": "https://api.spotify.com/v1/audio-analysis/0j1syF5BFSty3vFoaj0vsX", "duration_ms": 225040, "time_signature": 4}, {"danceability": 0.458, "energy": 0.816, "key": 0, "loudness": -6.793, "mode": 1, "speechiness": 0.0516, "acousticness": 0.244, "instrumentalness": 0, "liveness": 0.729, "valence": 0.465, "tempo": 144.458, "type": "audio_features", "id": "5J4lRkS1Vbe24XkomHNaY6", "uri": "spotify:track:5J4lRkS1Vbe24XkomHNaY6", "track_href": "https://api.spotify.com/v1/tracks/5J4lRkS1Vbe24XkomHNaY6", "analysis_url": "https://api.spotify.com/v1/audio-analysis/5J4lRkS1Vbe24XkomHNaY6", "duration_ms": 268000, "time_signature": 4}, {"danceability": 0.518, "energy": 0.8, "key": 11, "loudness": -7.933, "mode": 1, "speechiness": 0.0378, "acousticness": 0.694, "instrumentalness": 0.0835, "liveness": 0.758, "valence": 0.728, "tempo": 97.723, "type": "audio_features", "id": "6jrwEHluHDKsSqOF5oQzeY", "uri": "spotify:track:6jrwEHluHDKsSqOF5oQzeY", "track_href": "https://api.spotify.com/v1/tracks/6jrwEHluHDKsSqOF5oQzeY", "analysis_url": "https://api.spotify.com/v1/audio-analysis/6jrwEHluHDKsSqOF5oQzeY", "duration_ms": 270987, "time_signature": 4}, {"danceability": 0.489, "energy": 0.85, "key": 2, "loudness": -6.854, "mode": 1, "speechiness": 0.0803, "acousticness": 0.45, "instrumentalness": 0, "liveness": 0.893, "valence": 0.365, "tempo": 114.804, "type": "audio_features", "id": "38FDMr7uV4r4fgNx1McH1a", "uri": "spotify:track:38FDMr7uV4r4fgNx1McH1a", "track_href": "https://api.spotify.com/v1/tracks/38FDMr7uV4r4fgNx1McH1a", "analysis_url": "https://api.spotify.com/v1/audio-analysis/38FDMr7uV4r4fgNx1McH1a", "duration_ms": 188253, "time_signature": 4}, {"danceability": 0.536, "energy": 0.809, "key": 11, "loudness": -7.574, "mode": 0, "speechiness": 0.0707, "acousticness": 0.628, "instrumentalness": 0, "liveness": 0.964, "valence": 0.46, "tempo": 95.04, "type": "audio_features", "id": "5LqdIFraDk9bpzD0pRoBdl", "uri": "spotify:track:5LqdIFraDk9bpzD0pRoBdl", "track_href": "https://api.spotify.com/v1/tracks/5LqdIFraDk9bpzD0pRoBdl", "analysis_url": "https://api.spotify.com/v1/audio-analysis/5LqdIFraDk9bpzD0pRoBdl", "duration_ms": 270982, "time_signature": 4}, {"danceability": 0.693, "energy": 0.509, "key": 4, "loudness": -9.343, "mode": 1, "speechiness": 0.154, "acousticness": 0.429, "instrumentalness": 0, "liveness": 0.799, "valence": 0.554, "tempo": 142.952, "type": "audio_features", "id": "2BfbIbgrFXULyZ44mlSpbn", "uri": "spotify:track:2BfbIbgrFXULyZ44mlSpbn", "track_href": "https://api.spotify.com/v1/tracks/2BfbIbgrFXULyZ44mlSpbn", "analysis_url": "https://api.spotify.com/v1/audio-analysis/2BfbIbgrFXULyZ44mlSpbn", "duration_ms": 211698, "time_signature": 4}, {"danceability": 0.438, "energy": 0.848, "key": 6, "loudness": -6.525, "mode": 0, "speechiness": 0.133, "acousticness": 0.341, "instrumentalness": 0, "liveness": 0.914, "valence": 0.646, "tempo": 88.159, "type": "audio_features", "id": "53tntHbFQwbigGYrTlNeER", "uri": "spotify:track:53tntHbFQwbigGYrTlNeER", "track_href": "https://api.spotify.com/v1/tracks/53tntHbFQwbigGYrTlNeER", "analysis_url": "https://api.spotify.com/v1/audio-analysis/53tntHbFQwbigGYrTlNeER", "duration_ms": 227560, "time_signature": 4}, {"danceability": 0.542, "energy": 0.751, "key": 5, "loudness": -7.894, "mode": 0, "speechiness": 0.0673, "acousticness": 0.832, "instrumentalness": 0, "liveness": 0.822, "valence": 0.69, "tempo": 88.609, "type": "audio_features", "id": "5GejbM2Nt1xpnqukq6dnzv", "uri": "spotify:track:5GejbM2Nt1xpnqukq6dnzv", "track_href": "https://api.spotify.com/v1/tracks/5GejbM2Nt1xpnqukq6dnzv", "analysis_url": "https://api.spotify.com/v1/audio-analysis/5GejbM2Nt1xpnqukq6dnzv", "duration_ms": 251107, "time_signature": 4}, {"danceability": 0.535, "energy": 0.782, "key": 7, "loudness": -6.268, "mode": 1, "speechiness": 0.0497, "acousticness": 0.73, "instrumentalness": 0.00059, "liveness": 0.0859, "valence": 0.614, "tempo": 86.937, "type": "audio_features", "id": "7twV4lkBhVToFi4oRCIYe2", "uri": "spotify:track:7twV4lkBhVToFi4oRCIYe2", "track_href": "https://api.spotify.com/v1/tracks/7twV4lkBhVToFi4oRCIYe2", "analysis_url": "https://api.spotify.com/v1/audio-analysis/7twV4lkBhVToFi4oRCIYe2", "duration_ms": 336191, "time_signature": 4}, {"danceability": 0.467, "energy": 0.68, "key": 0, "loudness": -9.941, "mode": 1, "speechiness": 0.0515, "acousticness": 0.791, "instrumentalness": 0, "liveness": 0.0824, "valence": 0.697, "tempo": 160.749, "type": "audio_features", "id": "6jzSeHm8d8Nujq2f2jsooZ", "uri": "spotify:track:6jzSeHm8d8Nujq2f2jsooZ", "track_href": "https://api.spotify.com/v1/tracks/6jzSeHm8d8Nujq2f2jsooZ", "analysis_url": "https://api.spotify.com/v1/audio-analysis/6jzSeHm8d8Nujq2f2jsooZ", "duration_ms": 174000, "time_signature": 4}, {"danceability": 0.634, "energy": 0.818, "key": 2, "loudness": -7.246, "mode": 1, "speechiness": 0.0437, "acousticness": 0.541, "instrumentalness": 2.89e-06, "liveness": 0.493, "valence": 0.896, "tempo": 93.303, "type": "audio_features", "id": "1q2GjugpJTsPsytIul0WYH", "uri": "spotify:track:1q2GjugpJTsPsytIul0WYH", "track_href": "https://api.spotify.com/v1/tracks/1q2GjugpJTsPsytIul0WYH", "analysis_url": "https://api.spotify.com/v1/audio-analysis/1q2GjugpJTsPsytIul0WYH", "duration_ms": 236827, "time_signature": 4}, {"danceability": 0.554, "energy": 0.713, "key": 0, "loudness": -8.19, "mode": 1, "speechiness": 0.0814, "acousticness": 0.181, "instrumentalness": 0, "liveness": 0.218, "valence": 0.476, "tempo": 81.988, "type": "audio_features", "id": "7AgDKs2scZ2aGbRW7Usd1o", "uri": "spotify:track:7AgDKs2scZ2aGbRW7Usd1o", "track_href": "https://api.spotify.com/v1/tracks/7AgDKs2scZ2aGbRW7Usd1o", "analysis_url": "https://api.spotify.com/v1/audio-analysis/7AgDKs2scZ2aGbRW7Usd1o", "duration_ms": 221520, "time_signature": 4}]